omni_x/__init__.py
omni_x/components/__init__.py
omni_x/components/archive/__init__.py
omni_x/components/archive/fs.py
omni_x/components/env_generator/__init__.py
omni_x/components/env_generator/llm.py
omni_x/components/evaluator/__init__.py
omni_x/components/evaluator/random.py
omni_x/components/index/faiss_st.py
omni_x/components/initializer/__init__.py
omni_x/components/initializer/noop.py
omni_x/components/initializer/uniform.py
omni_x/components/moi/__init__.py
omni_x/components/moi/llm.py
omni_x/components/task_generator/__init__.py
omni_x/components/task_generator/llm.py
omni_x/components/trainer/__init__.py
omni_x/components/trainer/noop.py
omni_x/core.py
omni_x/py.typed
omni_x/utils/__init__.py
omni_x/utils/env.py
omni_x/utils/llm/base.py
omni_x/utils/llm/batch/anthropic.py
omni_x/utils/llm/logging.py
omni_x/utils/llm/prompts.py
omni_x/utils/run.py
omni_x/utils/sandbox.py
omni_x/utils/smoke_test.py
omni_x/utils/task.py
omni_x/viz/__init__.py
omni_x/viz/__main__.py
omni_x/viz/generators.py
omni_x/viz/plots.py
omni_x/viz/render.py
omni_x/viz/templates/base.html
omni_x/viz/templates/index.html
omni_x/viz/templates/task.html
omni_x/viz/trees.py
omni_epix-0.1.23.dist-info/WHEEL
omni_epix-0.1.23.dist-info/METADATA
omni_epix-0.1.23.dist-info/RECORD
