Metadata-Version: 2.4
Name: omni-epix
Version: 0.1.23
Summary: OMNI-X: An open-ended learning library inspired by the OMNI-EPIC algorithm, with composable building blocks for creating AI-generating algorithms.
Author: Maximilian Wolf
Author-email: Maximilian Wolf <max@mwolf.dev>
License-Expression: MIT
Requires-Dist: filelock>=3.19.1
Requires-Dist: faiss-cpu>=1.12.0 ; extra == 'faiss-st'
Requires-Dist: sentence-transformers>=5.1.1 ; extra == 'faiss-st'
Requires-Dist: instructor>=1.11.3 ; extra == 'llm'
Requires-Dist: openai>=1.109.1 ; extra == 'llm'
Requires-Dist: docker>=7.1.0 ; extra == 'sandbox'
Requires-Dist: tyro>=0.9.32 ; extra == 'sandbox'
Requires-Dist: graphviz>=0.21 ; extra == 'viz'
Requires-Dist: jinja2>=3.1.6 ; extra == 'viz'
Requires-Dist: matplotlib>=3.10.7 ; extra == 'viz'
Requires-Dist: scikit-learn>=1.7.2 ; extra == 'viz'
Requires-Python: >=3.13, <3.14
Provides-Extra: faiss-st
Provides-Extra: llm
Provides-Extra: sandbox
Provides-Extra: viz
